
{"items":[{"name":"Bonsai.ZeroMQ","href":"Bonsai.ZeroMQ.html","topicHref":"Bonsai.ZeroMQ.html","topicUid":"Bonsai.ZeroMQ","items":[{"name":"ConvertToFrame","href":"Bonsai.ZeroMQ.ConvertToFrame.html","topicHref":"Bonsai.ZeroMQ.ConvertToFrame.html","topicUid":"Bonsai.ZeroMQ.ConvertToFrame"},{"name":"ConvertToString","href":"Bonsai.ZeroMQ.ConvertToString.html","topicHref":"Bonsai.ZeroMQ.ConvertToString.html","topicUid":"Bonsai.ZeroMQ.ConvertToString"},{"name":"Dealer","href":"Bonsai.ZeroMQ.Dealer.html","topicHref":"Bonsai.ZeroMQ.Dealer.html","topicUid":"Bonsai.ZeroMQ.Dealer"},{"name":"GetIdentity","href":"Bonsai.ZeroMQ.GetIdentity.html","topicHref":"Bonsai.ZeroMQ.GetIdentity.html","topicUid":"Bonsai.ZeroMQ.GetIdentity"},{"name":"ProxyBackend","href":"Bonsai.ZeroMQ.ProxyBackend.html","topicHref":"Bonsai.ZeroMQ.ProxyBackend.html","topicUid":"Bonsai.ZeroMQ.ProxyBackend"},{"name":"ProxyFrontend","href":"Bonsai.ZeroMQ.ProxyFrontend.html","topicHref":"Bonsai.ZeroMQ.ProxyFrontend.html","topicUid":"Bonsai.ZeroMQ.ProxyFrontend"},{"name":"Publisher","href":"Bonsai.ZeroMQ.Publisher.html","topicHref":"Bonsai.ZeroMQ.Publisher.html","topicUid":"Bonsai.ZeroMQ.Publisher"},{"name":"Pull","href":"Bonsai.ZeroMQ.Pull.html","topicHref":"Bonsai.ZeroMQ.Pull.html","topicUid":"Bonsai.ZeroMQ.Pull"},{"name":"Push","href":"Bonsai.ZeroMQ.Push.html","topicHref":"Bonsai.ZeroMQ.Push.html","topicUid":"Bonsai.ZeroMQ.Push"},{"name":"Request","href":"Bonsai.ZeroMQ.Request.html","topicHref":"Bonsai.ZeroMQ.Request.html","topicUid":"Bonsai.ZeroMQ.Request"},{"name":"Response","href":"Bonsai.ZeroMQ.Response.html","topicHref":"Bonsai.ZeroMQ.Response.html","topicUid":"Bonsai.ZeroMQ.Response"},{"name":"ResponseContext","href":"Bonsai.ZeroMQ.ResponseContext.html","topicHref":"Bonsai.ZeroMQ.ResponseContext.html","topicUid":"Bonsai.ZeroMQ.ResponseContext"},{"name":"Router","href":"Bonsai.ZeroMQ.Router.html","topicHref":"Bonsai.ZeroMQ.Router.html","topicUid":"Bonsai.ZeroMQ.Router"},{"name":"SendResponse","href":"Bonsai.ZeroMQ.SendResponse.html","topicHref":"Bonsai.ZeroMQ.SendResponse.html","topicUid":"Bonsai.ZeroMQ.SendResponse"},{"name":"SocketInfo","href":"Bonsai.ZeroMQ.SocketInfo.html","topicHref":"Bonsai.ZeroMQ.SocketInfo.html","topicUid":"Bonsai.ZeroMQ.SocketInfo"},{"name":"SocketType","href":"Bonsai.ZeroMQ.SocketType.html","topicHref":"Bonsai.ZeroMQ.SocketType.html","topicUid":"Bonsai.ZeroMQ.SocketType"},{"name":"Subscriber","href":"Bonsai.ZeroMQ.Subscriber.html","topicHref":"Bonsai.ZeroMQ.Subscriber.html","topicUid":"Bonsai.ZeroMQ.Subscriber"},{"name":"ToMessage","href":"Bonsai.ZeroMQ.ToMessage.html","topicHref":"Bonsai.ZeroMQ.ToMessage.html","topicUid":"Bonsai.ZeroMQ.ToMessage"}]}],"memberLayout":"SamePage"}
